borea/__init__.py
borea/datastruct/__init__.py
borea/datastruct/camera.py
borea/datastruct/dtm.py
borea/datastruct/gcp.py
borea/datastruct/shot.py
borea/datastruct/workdata.py
borea/format/__init__.py
borea/format/conl.py
borea/format/rpc.py
borea/geodesy/__init__.py
borea/geodesy/approx_euclidean_proj.py
borea/geodesy/euclidean_proj.py
borea/geodesy/local_euclidean_proj.py
borea/geodesy/proj_engine.py
borea/geodesy/transform_geodesy.py
borea/geodesy/projectionlist/__init__.py
borea/geodesy/projectionlist/search_proj.py
borea/process/__init__.py
borea/process/p_add_data/__init__.py
borea/process/p_add_data/p_add_shot.py
borea/process/p_add_data/p_file_gcp2d.py
borea/process/p_add_data/p_file_gcp3d.py
borea/process/p_add_data/p_gen_param.py
borea/process/p_add_data/p_proj.py
borea/process/p_add_data/p_pt2d.py
borea/process/p_add_data/p_pt3d.py
borea/process/p_add_data/p_unit_shot.py
borea/process/p_add_data/p_write.py
borea/process/p_format/__init__.py
borea/process/p_format/p_read_opk.py
borea/process/p_format/p_write_con.py
borea/process/p_format/p_write_opk.py
borea/process/p_format/p_write_rpc.py
borea/process/p_func/__init__.py
borea/process/p_func/p_control.py
borea/process/p_func/p_image_world.py
borea/process/p_func/p_spaceresection.py
borea/process/p_func/p_tf_proj_pt.py
borea/process/p_func/p_world_image.py
borea/reader/__init__.py
borea/reader/reader_camera.py
borea/reader/reader_point.py
borea/reader/orientation/__init__.py
borea/reader/orientation/manage_reader.py
borea/reader/orientation/reader_opk.py
borea/stat/__init__.py
borea/stat/statistics.py
borea/transform_world_image/__init__.py
borea/transform_world_image/transform_dtm/__init__.py
borea/transform_world_image/transform_dtm/world_image_dtm.py
borea/transform_world_image/transform_shot/__init__.py
borea/transform_world_image/transform_shot/conversion_coor_shot.py
borea/transform_world_image/transform_shot/image_world_shot.py
borea/transform_world_image/transform_shot/world_image_shot.py
ign_borea-0.2.2.dist-info/LICENSE
ign_borea-0.2.2.dist-info/METADATA
ign_borea-0.2.2.dist-info/WHEEL
ign_borea-0.2.2.dist-info/entry_points.txt
ign_borea-0.2.2.dist-info/top_level.txt
ign_borea-0.2.2.dist-info/RECORD
