Metadata-Version: 2.1
Name: ign-borea
Version: 0.2.2
Summary: A package to manipulate orientation files
Author-email: Antoine Cornu <antoine.cornu@ign.fr>, Nicolas Laurain <nicolas.laurain@ign.fr>
License: MIT License
Project-URL: Github, https://github.com/ACornuIGN/Pink_Lady
Keywords: ign-borea,borea,aero,ign
Classifier: License :: OSI Approved :: MIT License
Classifier: Programming Language :: Python :: 3.9
Classifier: Programming Language :: Python :: 3.10
Classifier: Operating System :: Microsoft :: Windows
Classifier: Operating System :: Unix
Classifier: Operating System :: MacOS
Requires-Python: >=3.9
License-File: LICENSE
Requires-Dist: numpy <=1.26.4
Requires-Dist: dataclasses
Requires-Dist: pyproj
Requires-Dist: scipy
Requires-Dist: pandas
Provides-Extra: dev
Requires-Dist: numpy <=1.26.4 ; extra == 'dev'
Requires-Dist: pylint ; extra == 'dev'
Requires-Dist: pytest ; extra == 'dev'
Requires-Dist: pytest-shutil ; extra == 'dev'
Requires-Dist: flake8 ; extra == 'dev'
Requires-Dist: sphinx ; extra == 'dev'
Requires-Dist: furo ; extra == 'dev'
Requires-Dist: dataclasses ; extra == 'dev'
Requires-Dist: pyproj ; extra == 'dev'
Requires-Dist: scipy ; extra == 'dev'
Requires-Dist: pandas ; extra == 'dev'
